setup.py
streamlit_flow/__init__.py
streamlit_flow.egg-info/PKG-INFO
streamlit_flow.egg-info/SOURCES.txt
streamlit_flow.egg-info/dependency_links.txt
streamlit_flow.egg-info/top_level.txt