Metadata-Version: 2.1
Name: streamlit-flow
Version: 0.1.0
Summary: Create multipage streamlit applications
Home-page: UNKNOWN
Author: Hans Then
Author-email: hans.then@gmail.com
License: UNKNOWN
Platform: UNKNOWN
Classifier: Programming Language :: Python :: 3
Classifier: License :: OSI Approved :: MIT License
Classifier: Operating System :: OS Independent
Requires-Python: >=3.8
